detox/__init__.py
detox/__main__.py
detox/cli.py
detox/proc.py
detox/tox_proclimit.py
detox-0.19.dist-info/LICENSE
detox-0.19.dist-info/METADATA
detox-0.19.dist-info/WHEEL
detox-0.19.dist-info/entry_points.txt
detox-0.19.dist-info/top_level.txt
detox-0.19.dist-info/RECORD
